djangae/__init__.py
djangae/admin.py
djangae/apps.py
djangae/checks.py
djangae/environment.py
djangae/models.py
djangae/processing.py
djangae/sandbox.py
djangae/settings_base.py
djangae/storage.py
djangae/test.py
djangae/urls.py
djangae/utils.py
djangae/views.py
djangae/contrib/__init__.py
djangae/contrib/sleuth.py
djangae/contrib/backup/__init__.py
djangae/contrib/backup/tasks.py
djangae/contrib/backup/urls.py
djangae/contrib/backup/utils.py
djangae/contrib/backup/views.py
djangae/contrib/backup/tests/__init__.py
djangae/contrib/backup/tests/test_tasks.py
djangae/contrib/backup/tests/test_utils.py
djangae/contrib/backup/tests/test_views.py
djangae/contrib/common/__init__.py
djangae/contrib/common/middleware.py
djangae/contrib/googleauth/__init__.py
djangae/contrib/googleauth/admin.py
djangae/contrib/googleauth/apps.py
djangae/contrib/googleauth/decorators.py
djangae/contrib/googleauth/middleware.py
djangae/contrib/googleauth/models.py
djangae/contrib/googleauth/permissions.py
djangae/contrib/googleauth/urls.py
djangae/contrib/googleauth/views.py
djangae/contrib/googleauth/backends/__init__.py
djangae/contrib/googleauth/backends/base.py
djangae/contrib/googleauth/backends/iap.py
djangae/contrib/googleauth/backends/oauth2.py
djangae/contrib/googleauth/templates/googleauth/dev_login.html
djangae/contrib/googleauth/tests/__init__.py
djangae/contrib/googleauth/tests/test_iap.py
djangae/contrib/googleauth/tests/test_local_iap_middleware.py
djangae/contrib/googleauth/tests/test_middleware.py
djangae/contrib/googleauth/tests/test_oauth.py
djangae/contrib/googleauth/tests/test_views.py
djangae/contrib/locking/__init__.py
djangae/contrib/locking/admin.py
djangae/contrib/locking/kinds.py
djangae/contrib/locking/lock.py
djangae/contrib/locking/memcache.py
djangae/contrib/locking/models.py
djangae/contrib/locking/tests.py
djangae/contrib/locking/urls.py
djangae/contrib/locking/views.py
djangae/contrib/pagination/__init__.py
djangae/contrib/pagination/decorators.py
djangaec-2.0.0rc3.dist-info/LICENSE.md
djangaec-2.0.0rc3.dist-info/METADATA
djangaec-2.0.0rc3.dist-info/WHEEL
djangaec-2.0.0rc3.dist-info/top_level.txt
djangaec-2.0.0rc3.dist-info/RECORD
