Metadata-Version: 2.1
Name: djangaec
Version: 2.0.0rc3
Summary: Django integration with Google App Engine GC Custom Build
Home-page: https://github.com/potatolondon/djangae
Author: GC
Author-email: kotarskip@googl.com
License: UNKNOWN
Keywords: django,Google App Engine,GAE
Platform: UNKNOWN
Classifier: Development Status :: 4 - Beta
Classifier: Framework :: Django
Classifier: Framework :: Django :: 2.2
Classifier: Framework :: Django :: 3.0
Classifier: Framework :: Django :: 3.1
Classifier: Framework :: Django :: 3.2
Classifier: Intended Audience :: Developers
Classifier: License :: OSI Approved :: BSD License
Classifier: Operating System :: OS Independent
Classifier: Programming Language :: Python
Requires-Dist: django<=3.3.4,>=2.2
Requires-Dist: django-gcloud-connectors>=0.3.4
Requires-Dist: google-api-python-client>=1.7.11
Requires-Dist: google-cloud-tasks<2.0.0,>=1.5.0
Requires-Dist: psutil>=5.7.3
Requires-Dist: requests>=2.22.0
Requires-Dist: cryptography==3.4.6
Requires-Dist: python-jose[cryptography]==3.2.0
Provides-Extra: test
Requires-Dist: beautifulsoup4; extra == "test"
